KNOWN_READER_ISSUES.rst
MANIFEST.in
README.rst
setup.cfg
setup.py
tox.ini
mwlib/__init__.py
mwlib.epub.egg-info/PKG-INFO
mwlib.epub.egg-info/SOURCES.txt
mwlib.epub.egg-info/dependency_links.txt
mwlib.epub.egg-info/entry_points.txt
mwlib.epub.egg-info/namespace_packages.txt
mwlib.epub.egg-info/not-zip-safe
mwlib.epub.egg-info/requires.txt
mwlib.epub.egg-info/top_level.txt
mwlib/epub/__init__.py
mwlib/epub/_version.py
mwlib/epub/collection.py
mwlib/epub/config.py
mwlib/epub/epubwriter.py
mwlib/epub/metainfo.py
mwlib/epub/mimetype
mwlib/epub/siteconfig.py
mwlib/epub/treeprocessor.py
mwlib/epub/wikipedia_logo.jpg
mwlib/epub/wp.css
mwlib/epub/utils/__init__.py
mwlib/epub/utils/allowed_attributes.json
mwlib/epub/utils/allowed_tags.json
mwlib/epub/utils/empty_ok.json
mwlib/epub/utils/make_tag_attr_list.py
mwlib/epub/utils/misc.py
tests/test.zip
tests/test_basic.py
tests/test_valid_xhtml.py