Metadata-Version: 1.0
Name: mwlib.epub
Version: 0.14.3
Summary: generate epub files from mediawiki markup
Home-page: http://code.pediapress.com/
Author: pediapress.com
Author-email: info@pediapress.com
License: BSD License
Platform: UNKNOWN
